LICENSE.txt
README.md
pyproject.toml
setup.cfg
setup.py
intvalpy/__init__.py
intvalpy.egg-info/PKG-INFO
intvalpy.egg-info/SOURCES.txt
intvalpy.egg-info/dependency_links.txt
intvalpy.egg-info/not-zip-safe
intvalpy.egg-info/requires.txt
intvalpy.egg-info/top_level.txt
intvalpy/kernel/__init__.py
intvalpy/kernel/abstract.py
intvalpy/kernel/elementary_functions.py
intvalpy/kernel/interval_arithmetics.pyx
intvalpy/kernel/new_objects.py
intvalpy/kernel/preprocessing.py
intvalpy/kernel/ralgb5.py
intvalpy/kernel/real_intervals.py
intvalpy/kernel/utils.py
intvalpy/kernel/visualization.py
intvalpy/linear/ChebNorm.py
intvalpy/linear/Gauss.py
intvalpy/linear/Gauss_Seidel.py
intvalpy/linear/HBR.py
intvalpy/linear/Neumaier.py
intvalpy/linear/PPS.py
intvalpy/linear/PSS.py
intvalpy/linear/Rohn.py
intvalpy/linear/Subdiff.py
intvalpy/linear/Tol.py
intvalpy/linear/Uni.py
intvalpy/linear/Uss.py
intvalpy/linear/__init__.py
intvalpy/linear/boundary_intervals.py
intvalpy/linear/system_properties.py
intvalpy/models/ISPAE.py
intvalpy/models/WILS.py
intvalpy/models/__init__.py
intvalpy/nonlinear/__init__.py
intvalpy/nonlinear/external_evaluation.py
intvalpy/nonlinear/globopt.py
intvalpy/nonlinear/recognizing_functional.py
intvalpy/nonlinear/solution_existence.py
test/test_basic.py