Metadata-Version: 2.1
Name: intvalpy
Version: 2.0.2
Summary: IntvalPy -- a Python interval computation library
Home-page: https://github.com/AndrosovAS/intvalpy
Author: Androsov, Artem Stanislavovich and Shary, Sergey Petrovich
Author-email: astandrosov@yandex.ru, shary@ict.nsc.ru
License: MIT License
Keywords: interval,machine learning,data fitting,inequality visualization,optimal solutions,math
License-File: LICENSE.txt
Requires-Dist: matplotlib
Requires-Dist: numpy
Requires-Dist: cvxopt
Requires-Dist: mpmath
Requires-Dist: pandas
Requires-Dist: cython
